grobidmonkey/__init__.py
grobidmonkey/reader.py
grobidmonkey/utils.py
grobidmonkey/methods/lxmlmethod.py
grobidmonkey/methods/monkeymethod.py
grobidmonkey/methods/x2dmethod.py
grobidmonkey-0.0.4.dist-info/METADATA
grobidmonkey-0.0.4.dist-info/WHEEL
grobidmonkey-0.0.4.dist-info/licenses/LICENSE
grobidmonkey-0.0.4.dist-info/RECORD
