Metadata-Version: 2.1
Name: grobidmonkey
Version: 0.0.4
Summary: A python package for processing grobid output.
Project-URL: Homepage, https://github.com/com3dian/grobidmonkey
Project-URL: Issues, https://github.com/com3dian/grobidmonkey/issues
Author-email: Zehao Lu <com3dian@outlook.com>
License-File: LICENSE
Classifier: License :: OSI Approved :: MIT License
Classifier: Operating System :: OS Independent
Classifier: Programming Language :: Python :: 3
Requires-Python: >=3.8
Requires-Dist: anytree
Requires-Dist: lxml
Requires-Dist: xmltodict
